Metadata-Version: 2.1
Name: ciqw
Version: 0.4.9
Summary: Connect IQ Wrapper
Home-page: UNKNOWN
Author: Jean Schurger
Author-email: jean@schurger.org
License: GPLv3
Platform: UNKNOWN
License-File: COPYING
